webdriver_kaifuku/__init__.py
webdriver_kaifuku/tries.py
webdriver_kaifuku-25.10.22.dist-info/METADATA
webdriver_kaifuku-25.10.22.dist-info/WHEEL
webdriver_kaifuku-25.10.22.dist-info/licenses/LICENSE
webdriver_kaifuku-25.10.22.dist-info/RECORD
