Metadata-Version: 2.4
Name: webdriver_kaifuku
Version: 25.10.22
Summary: Restartable webdriver instances
Project-URL: repository, https://github.com/RedHatQE/webdriver_kaifuku
Maintainer-email: Ronny Pfannschmidt <rpfannsc@redhat.com>, Nikhil Dhandre <ndhandre@redhat.com>
License-File: LICENSE
Keywords: selenium
Classifier: License :: OSI Approved :: Mozilla Public License 2.0 (MPL 2.0)
Classifier: Programming Language :: Python :: 3 :: Only
Classifier: Programming Language :: Python :: 3.8
Classifier: Programming Language :: Python :: 3.9
Classifier: Programming Language :: Python :: 3.10
Classifier: Programming Language :: Python :: 3.11
Classifier: Programming Language :: Python :: 3.12
Classifier: Programming Language :: Python :: 3.13
Classifier: Topic :: Software Development :: Quality Assurance
Classifier: Topic :: Software Development :: Testing
Requires-Python: >=3.8
Requires-Dist: attrs
Requires-Dist: requests
Requires-Dist: selenium>=4.0.0
Provides-Extra: test
Requires-Dist: pytest; extra == 'test'
Requires-Dist: wait-for; extra == 'test'
